odoo/addons/energy_communities_l10n_es_ticketbai/__init__.py
odoo/addons/energy_communities_l10n_es_ticketbai/__manifest__.py
odoo/addons/energy_communities_l10n_es_ticketbai/wizard/__init__.py
odoo/addons/energy_communities_l10n_es_ticketbai/wizard/ticketbai_info.py
odoo_addon_energy_communities_l10n_es_ticketbai-16.0.0.1.0.dist-info/METADATA
odoo_addon_energy_communities_l10n_es_ticketbai-16.0.0.1.0.dist-info/WHEEL
odoo_addon_energy_communities_l10n_es_ticketbai-16.0.0.1.0.dist-info/top_level.txt
odoo_addon_energy_communities_l10n_es_ticketbai-16.0.0.1.0.dist-info/RECORD
