Metadata-Version: 2.1
Name: odoo-addon-energy-communities-l10n-es-ticketbai
Version: 16.0.0.1.0
Summary: energy_communities_l10n_es_ticketbai
Home-page: https://git.coopdevs.org/coopdevs/comunitats-energetiques/odoo-ce
Author: Som IT SCCL & Som Energia SCCL
License: AGPL-3
Classifier: Programming Language :: Python
Classifier: Framework :: Odoo
Classifier: Framework :: Odoo :: 16.0
Classifier: License :: OSI Approved :: GNU Affero General Public License v3
Requires-Python: >=3.10
Requires-Dist: odoo-addon-l10n-es-ticketbai <16.1dev,>=16.0dev
Requires-Dist: odoo <16.1dev,>=16.0a
